urlshortening/__init__.py
urlshortening/admin.py
urlshortening/apps.py
urlshortening/models.py
urlshortening/testsettings.py
urlshortening/urls.py
urlshortening/views.py
urlshortening/migrations/0001_initial.py
urlshortening/migrations/__init__.py
urlshortening/tests/__init__.py
urlshortening/tests/test_model.py
urlshortening/tests/test_view.py
django_url_shortening_2-1.0.0.dist-info/LICENSE
django_url_shortening_2-1.0.0.dist-info/METADATA
django_url_shortening_2-1.0.0.dist-info/WHEEL
django_url_shortening_2-1.0.0.dist-info/top_level.txt
django_url_shortening_2-1.0.0.dist-info/RECORD
