Metadata-Version: 2.1
Name: django-url-shortening-2
Version: 1.0.0
Summary: A URL shortening app for Django.
Home-page: https://github.com/shkhaksar/django-url-shortening
Author: Doubletapp
Author-email: info@doubletapp.ru
License: BSD
Classifier: Development Status :: 5 - Production/Stable
Classifier: Framework :: Django
Classifier: Intended Audience :: Developers
Classifier: License :: OSI Approved :: BSD License
Classifier: Operating System :: OS Independent
Classifier: Programming Language :: Python :: 3.5
Classifier: Topic :: Internet :: WWW/HTTP
License-File: LICENSE
Requires-Dist: six
